MANIFEST.in
README.md
setup.py
tox.ini
rc_cts/LICENSE
rc_cts/__init__.py
rc_cts.egg-info/PKG-INFO
rc_cts.egg-info/SOURCES.txt
rc_cts.egg-info/dependency_links.txt
rc_cts.egg-info/entry_points.txt
rc_cts.egg-info/requires.txt
rc_cts.egg-info/top_level.txt
rc_cts/components/__init__.py
rc_cts/components/searcher_example.py
rc_cts/components/threat_webservice.py
rc_cts/data/app.config.cts
rc_cts/lib/__init__.py
rc_cts/lib/resilient_mock.py
rc_cts/lib/threat_models.py
tests/test_webserver.py