Metadata-Version: 1.1
Name: rc-cts
Version: 32.0.140
Summary: Resilient Circuits Custom Threat Service
Home-page: https://github.com/ibmresilient/resilient-circuits-packages
Author: IBM Resilient
Author-email: support@resilientsystems.com
License: MIT
Platform: any
Classifier: Programming Language :: Python
